{"body":"### Have you searched if there an existing feature request for this?\n\n- [x] I have searched the existing requests\n\n### Feature description\n\n### Is your feature request related to a problem? Please describe.\nCurrently, there is no way to quickly check the installed version of Scrapling from the command line. Users have to resort to `pip show scrapling` or Python one-liners like `python -c \"import scrapling; print(scrapling.__version__)\"`. This is inconvenient, especially when debugging, reporting bugs, or writing documentation that references a specific version.\n\n### Describe the solution you'd like\nAdd a `--version` flag to the CLI that prints the current Scrapling version and exits. For example:\n\n```bash\n$ scrapling --version\nScrapling, version 0.4.8","labels":[{"id":"LA_kwDOM_t66c8AAAABxOlrgw","name":"enhancement","description":"New feature or request","color":"a2eeef"}],"number":299,"title":"[Feature Request] Add `--version` flag to CLI","url":"https://github.com/D4Vinci/Scrapling/issues/299"}
